tests/__init__.py
tests/test_ids/__init__.py
tests/test_ids/test_ids.py
tests/test_ids/test_load_protos.py
tests/test_ids/test_task_util.py
ymir/__init__.py
ymir/ids/__init__.py
ymir/ids/class_ids.py
ymir/ids/task_id.py
ymir/ids/type_id_names.csv
ymir/ids/type_id_names.py
ymir/protos/__init__.py
ymir/protos/mir_common_pb2.py
ymir/protos/mir_controller_service_pb2.py
ymir/protos/mir_controller_service_pb2_grpc.py
ymir_proto-0.1.5.dist-info/LICENSE
ymir_proto-0.1.5.dist-info/METADATA
ymir_proto-0.1.5.dist-info/WHEEL
ymir_proto-0.1.5.dist-info/top_level.txt
ymir_proto-0.1.5.dist-info/RECORD
