Metadata-Version: 2.1
Name: ymir-proto
Version: 0.1.5
Summary: YMIR Protobuf Specs
Home-page: UNKNOWN
License: UNKNOWN
Platform: UNKNOWN
Classifier: Programming Language :: Python :: 3
License-File: LICENSE
